README.txt
setup.cfg
setup.py
DoDoStorage.egg-info/PKG-INFO
DoDoStorage.egg-info/SOURCES.txt
DoDoStorage.egg-info/dependency_links.txt
DoDoStorage.egg-info/requires.txt
DoDoStorage.egg-info/top_level.txt
dodostorage/__init__.py
dodostorage/backend.py
dodostorage/client.py
dodostorage/dodoserver
dodostorage/test.py
scrips/ocr.py
scrips/savedb.py
scrips/scanner.sh
