Metadata-Version: 1.0
Name: DoDoStorage
Version: 0.3.dev-r2016
Summary: User-Space write-once Network Filesystem
Home-page: http://www.hudora.de/code/
Author: Maximillian Dornseif
Author-email: md@hudora.de
License: BSD
Platform: UNKNOWN
Classifier: Intended Audience :: Developers
Classifier: Programming Language :: Python
